candlekit/__init__.py
candlekit/entity.py
candlekit/patterns.py
candlekit/utils.py
candlekit/tests/__init__.py
candlekit/tests/test_entity.py
candlekit/tests/test_patterns.py
candlekit/tests/test_utils.py
py_candlekit-1.0.1.dist-info/licenses/LICENSE
py_candlekit-1.0.1.dist-info/METADATA
py_candlekit-1.0.1.dist-info/WHEEL
py_candlekit-1.0.1.dist-info/top_level.txt
py_candlekit-1.0.1.dist-info/RECORD
