Metadata-Version: 2.4
Name: py-candlekit
Version: 1.0.1
Summary: A lightweight, pandas-friendly Python library for detecting candlestick patterns in financial time-series data, based on NISON book.
Author-email: Zhiro Dadkhah <zhirodadkhah@hotmail.com>
License: MIT
Project-URL: Homepage, https://github.com/zhirodadkhah/candlekit
Project-URL: Repository, https://github.com/zhirodadkhah/candlekit
Project-URL: Bug Tracker, https://github.com/zhirodadkhah/candlekit/issues
Keywords: candlestick,technical-analysis,trading,finance,pandas,pattern-recognition,NISON patterns
Classifier: Intended Audience :: Financial and Insurance Industry
Classifier: Intended Audience :: Science/Research
Classifier: License :: OSI Approved :: MIT License
Classifier: Operating System :: OS Independent
Classifier: Programming Language :: Python :: 3
Classifier: Programming Language :: Python :: 3.8
Classifier: Programming Language :: Python :: 3.9
Classifier: Programming Language :: Python :: 3.10
Classifier: Programming Language :: Python :: 3.11
Classifier: Programming Language :: Python :: 3.12
Classifier: Topic :: Office/Business :: Financial :: Investment
Classifier: Topic :: Scientific/Engineering :: Information Analysis
Requires-Python: >=3.8
License-File: LICENSE
Requires-Dist: pandas>=1.3.0
Requires-Dist: numpy>=1.21.0
Provides-Extra: dev
Requires-Dist: pytest>=7.0.0; extra == "dev"
Requires-Dist: pytest-cov>=4.0.0; extra == "dev"
Dynamic: license-file
